pitchly/__init__.py
pitchly/__main__.py
pitchly/cli.py
pitchly/metrica.py
pitchly/metrica_old.py
pitchly/params.py
pitchly/pitch.py
pitchly/pitch_control.py
pitchly/pitch_control_old.py
pitchly/utils.py
pitchly-0.2.2.dist-info/AUTHORS.rst
pitchly-0.2.2.dist-info/LICENSE
pitchly-0.2.2.dist-info/METADATA
pitchly-0.2.2.dist-info/WHEEL
pitchly-0.2.2.dist-info/entry_points.txt
pitchly-0.2.2.dist-info/top_level.txt
pitchly-0.2.2.dist-info/RECORD
