Metadata-Version: 2.1
Name: pitchly
Version: 0.2.2
Summary: A python package that is a wrapper for Plotly to generate football tracking and event data plots
Home-page: https://github.com/opunsoars/pitchly
Author: Vinay Warrier
Author-email: vinay.warrier@gmail.com
License: MIT
Project-URL: Documentation, https://pitchly.readthedocs.io/
Project-URL: Changelog, https://pitchly.readthedocs.io/en/latest/changelog.html
Project-URL: Issue Tracker, https://github.com/opunsoars/pitchly/issues
Platform: UNKNOWN
Classifier: Development Status :: 5 - Production/Stable
Classifier: Intended Audience :: Developers
Classifier: Intended Audience :: Science/Research
Classifier: License :: OSI Approved :: MIT License
Classifier: Operating System :: Unix
Classifier: Operating System :: POSIX
Classifier: Operating System :: Microsoft :: Windows
Classifier: Programming Language :: Python
Classifier: Programming Language :: Python :: 3
Classifier: Programming Language :: Python :: 3 :: Only
Classifier: Programming Language :: Python :: 3.6
Classifier: Programming Language :: Python :: 3.7
Classifier: Programming Language :: Python :: 3.8
Classifier: Programming Language :: Python :: 3.9
Classifier: Programming Language :: Python :: Implementation :: CPython
Classifier: Programming Language :: Python :: Implementation :: PyPy
Classifier: Topic :: Scientific/Engineering
Requires-Python: >=3.6
Requires-Dist: tqdm (==4.50.2)
Requires-Dist: scipy (>=1.5.2)
Requires-Dist: Jinja2 (>=2.11.2)
Requires-Dist: plotly (>=4.14.3)
Requires-Dist: pandas (>=1.1.3)
Requires-Dist: numpy (>=1.19.2)
